sonic_arabic/__init__.py
sonic_arabic/audio_pipeline.py
sonic_arabic/ner/__init__.py
sonic_arabic/ner/ner_analysis.py
sonic_arabic/ner/arabic_ner/__init__.py
sonic_arabic/ner/arabic_ner/helpers.py
sonic_arabic/ner/arabic_ner/tagger.py
sonic_arabic/punctuation/__init__.py
sonic_arabic/punctuation/punctuation_analysis.py
sonic_arabic/punctuation/BertPuncCap/__init__.py
sonic_arabic/punctuation/BertPuncCap/benchmark.py
sonic_arabic/punctuation/BertPuncCap/data_handler.py
sonic_arabic/punctuation/BertPuncCap/model.py
sonic_arabic/punctuation/BertPuncCap/report_writer.py
sonic_arabic/punctuation/BertPuncCap/repunc_recap.py
sonic_arabic/punctuation/BertPuncCap/train.py
sonic_arabic/punctuation/BertPuncCap/trainer.py
sonic_arabic/punctuation/BertPuncCap/utils.py
sonic_arabic/punctuation/BertPuncCap/data/__init__.py
sonic_arabic/punctuation/BertPuncCap/models/__init__.py
sonic_arabic/punctuation/BertPuncCap/models/mbert_base_cased_8langs/__init__.py
sonic_arabic/sentiment/__init__.py
sonic_arabic/sentiment/sentiment_analysis.py
sonic_arabic/transcriber/__init__.py
sonic_arabic/transcriber/transcribe_analysis.py
sonic_arabic/utils_arabic/__init__.py
sonic_arabic/utils_arabic/download_model.py
sonic_arabic/utils_arabic/utils.py
sonic_arabic-1.0.0.dist-info/METADATA
sonic_arabic-1.0.0.dist-info/WHEEL
sonic_arabic-1.0.0.dist-info/top_level.txt
sonic_arabic-1.0.0.dist-info/RECORD
