Metadata-Version: 2.1
Name: sonic-arabic
Version: 1.0.0
Summary: анализ арабской речи
Home-page: https://git.id-network.ru/data-science/sc_ar
Author: i.karpenko
Author-email: volgakarp@gmail.com
Classifier: Programming Language :: Python :: 3.9
Requires-Python: >=3.9
Requires-Dist: openai-whisper (==20230314)
Requires-Dist: camel-tools (==1.5.2)
Requires-Dist: torch (==2.0.1)
Requires-Dist: transformers (==4.33.1)
Requires-Dist: tqdm (==4.66.1)
Requires-Dist: gdown (==4.7.1)
